base_utils/__init__.py
base_utils/dtos.py
base_utils/exception.py
base_utils/utils.py
c_h_base-0.0.1.dist-info/METADATA
c_h_base-0.0.1.dist-info/WHEEL
c_h_base-0.0.1.dist-info/top_level.txt
c_h_base-0.0.1.dist-info/RECORD
